maliput_malidrive/LICENSE.txt
maliput_malidrive/__init__.py
maliput_malidrive/libmaliput_malidrive_road_network.so
maliput_malidrive.egg-info/PKG-INFO
maliput_malidrive.egg-info/SOURCES.txt
maliput_malidrive.egg-info/dependency_links.txt
maliput_malidrive.egg-info/entry_points.txt
maliput_malidrive.egg-info/top_level.txt
maliput_malidrive.libs/libgomp-e985bcbb.so.1.0.0
maliput_malidrive.libs/libmaliput_analysis-f88c9fb5.so
maliput_malidrive.libs/libmaliput_api-b537e156.so
maliput_malidrive.libs/libmaliput_base-7b565adc.so
maliput_malidrive.libs/libmaliput_common-135e84b8.so
maliput_malidrive.libs/libmaliput_common_trajectories-3ae15db7.so
maliput_malidrive.libs/libmaliput_drake-962bc0a3.so
maliput_malidrive.libs/libmaliput_drake_common-ca30d237.so
maliput_malidrive.libs/libmaliput_framework-74a90d72.so
maliput_malidrive.libs/libmaliput_geometry_base-f8f0324e.so
maliput_malidrive.libs/libmaliput_malidrive_base-893c852b.so
maliput_malidrive.libs/libmaliput_malidrive_builder-dac5dc3c.so
maliput_malidrive.libs/libmaliput_malidrive_common-e2203bc0.so
maliput_malidrive.libs/libmaliput_malidrive_road_curve-eb0078f9.so
maliput_malidrive.libs/libmaliput_malidrive_xodr-98af80fe.so
maliput_malidrive.libs/libmaliput_math-e136a818.so
maliput_malidrive.libs/libmaliput_plugin-539d988c.so
maliput_malidrive.libs/libmaliput_routing-17ecbfe1.so
maliput_malidrive.libs/libmaliput_utility-ea5cb19e.so
maliput_malidrive.libs/libtinyxml2-698443f7.so.7.1.0
maliput_malidrive.libs/libyaml-cpp-a71b8053.so.0.7.0
maliput_malidrive-0.12.1.dist-info/METADATA
maliput_malidrive-0.12.1.dist-info/WHEEL
maliput_malidrive-0.12.1.dist-info/entry_points.txt
maliput_malidrive-0.12.1.dist-info/top_level.txt
maliput_malidrive-0.12.1.dist-info/RECORD
