Metadata-Version: 2.1
Name: maliput_malidrive
Version: 0.12.1
Summary: OpenDRIVE-based maliput backend.
Home-page: https://github.com/maliput/maliput_malidrive
Author: Franco Cipollone
Keywords: maliput_malidrive
Requires-Python: >=3.8
